sharepointcacheprimer/__init__.py
sharepointcacheprimer/cmdline.py
sharepointcacheprimer/primer.py
sharepointcacheprimer-1.0b3.post5.data/data/doc/example.ini
sharepointcacheprimer-1.0b3.post5.dist-info/DESCRIPTION.rst
sharepointcacheprimer-1.0b3.post5.dist-info/entry_points.txt
sharepointcacheprimer-1.0b3.post5.dist-info/METADATA
sharepointcacheprimer-1.0b3.post5.dist-info/metadata.json
sharepointcacheprimer-1.0b3.post5.dist-info/RECORD
sharepointcacheprimer-1.0b3.post5.dist-info/top_level.txt
sharepointcacheprimer-1.0b3.post5.dist-info/WHEEL
