Metadata-Version: 2.0
Name: sharepointcacheprimer
Version: 1.0b3.post5
Summary: Cache Primer for Sharepoint with ADFSv3
Home-page: https://github.com/rjewell/sharepointcacheprimer
Author: Bob Jewell
Author-email: bob@disclosed.org
License: MIT
Keywords: sharepoint adfs cache
Platform: UNKNOWN
Classifier: Development Status :: 3 - Alpha
Classifier: Intended Audience :: Information Technology
Classifier: Topic :: System :: Systems Administration
Classifier: License :: OSI Approved :: MIT License
Classifier: Programming Language :: Python :: 3.4
Requires-Dist: robobrowser
